Metadata-Version: 2.1
Name: provideo-ferramentas-gledson
Version: 1.0
Summary: Este pacote irá fornecer ferramentas de processamento de video
Home-page: UNKNOWN
Author: Gledson Silva
Author-email: gle1984@gmail.com
License: UNKNOWN
Keywords: camera,video,processamento
Platform: UNKNOWN
License-File: license.txt
